virtulizorAdmin/__init__.py
virtulizorAdmin/admin.py
virtulizorAdmin-0.1.0.dist-info/LICENSE
virtulizorAdmin-0.1.0.dist-info/METADATA
virtulizorAdmin-0.1.0.dist-info/WHEEL
virtulizorAdmin-0.1.0.dist-info/top_level.txt
virtulizorAdmin-0.1.0.dist-info/RECORD
