Metadata-Version: 2.1
Name: virtulizorAdmin
Version: 0.1.0
Summary: A brief description of your library
Home-page: https://github.com/yourusername/virtulizorAdmin
Author: Your Name
Author-email: your.email@example.com
License: UNKNOWN
Platform: UNKNOWN
Classifier: Programming Language :: Python :: 3
Classifier: License :: OSI Approved :: MIT License
Classifier: Operating System :: OS Independent
Requires-Python: >=3.6
License-File: LICENSE
